.bumpversion.cfg
.gitignore
.travis.yml
AUTHORS.rst
CHANGELOG.rst
CONTRIBUTING.rst
LICENSE
MANIFEST.in
README.rst
setup.cfg
setup.py
nbs/getting_started.ipynb
nbs/hyperparameter_optimization.ipynb
nbs/worker_script.sh
src/autoCorrection/__init__.py
src/autoCorrection/autoencoder.py
src/autoCorrection/correctors.py
src/autoCorrection/data_utils.py
src/autoCorrection/default_values.py
src/autoCorrection/hyopt.py
src/autoCorrection/layers.py
src/autoCorrection/losses.py
src/autoCorrection/optimization.py
src/autoCorrection/optimization_data.py
src/autoCorrection/optimization_metrics.py
src/autoCorrection/optimization_model.py
src/autoCorrection.egg-info/PKG-INFO
src/autoCorrection.egg-info/SOURCES.txt
src/autoCorrection.egg-info/dependency_links.txt
src/autoCorrection.egg-info/not-zip-safe
src/autoCorrection.egg-info/requires.txt
src/autoCorrection.egg-info/top_level.txt
src/autoCorrection/data/skin_gtex.tsv.gz
src/autoCorrection/data/skin_small.tsv.gz
src/autoCorrection/data/wbl_br1_br2_bst_hrt_skn.tsv.gz
src/autoCorrection/data/whole_blood_gtex.tsv.gz
tests/test_BasicTesting.py
tests/test_autoCorrect.py